stackspot_client/__init__.py
stackspot_client/client.py
stackspot_client/knowledge_sources.py
stackspot_client/quick_commands.py
stackspot_client-0.1.7.dist-info/licenses/LICENSE
stackspot_client-0.1.7.dist-info/METADATA
stackspot_client-0.1.7.dist-info/WHEEL
stackspot_client-0.1.7.dist-info/top_level.txt
stackspot_client-0.1.7.dist-info/RECORD
