Metadata-Version: 2.4
Name: stackspot-client
Version: 0.1.7
Summary: Cliente Python para a API do StackSpot
Home-page: https://github.com/Kaiofprates/stackspot-client
Author: KaiofPrates
Author-email: kaiofprudencio@gmail.com
Maintainer: eltonjosesouza
Maintainer-email: github@eltonjose.com.br
Classifier: Programming Language :: Python :: 3
Classifier: License :: OSI Approved :: MIT License
Classifier: Operating System :: OS Independent
Requires-Python: >=3.7
License-File: LICENSE
Requires-Dist: requests>=2.31.0
Provides-Extra: env
Requires-Dist: python-dotenv>=1.1.0; extra == "env"
Dynamic: author
Dynamic: author-email
Dynamic: classifier
Dynamic: description
Dynamic: description-content-type
Dynamic: home-page
Dynamic: license-file
Dynamic: maintainer
Dynamic: maintainer-email
Dynamic: provides-extra
Dynamic: requires-dist
Dynamic: requires-python
Dynamic: summary
